LICENSE
MANIFEST.in
README.rst
setup.py
django_subdomains.egg-info/PKG-INFO
django_subdomains.egg-info/SOURCES.txt
django_subdomains.egg-info/dependency_links.txt
django_subdomains.egg-info/not-zip-safe
django_subdomains.egg-info/requires.txt
django_subdomains.egg-info/top_level.txt
subdomains/__init__.py
subdomains/middleware.py
subdomains/models.py
subdomains/utils.py
subdomains/compat/__init__.py
subdomains/compat/requestfactory.py
subdomains/compat/template.py
subdomains/compat/tests.py
subdomains/templatetags/__init__.py
subdomains/templatetags/subdomainurls.py
subdomains/tests/__init__.py
subdomains/tests/tests.py
subdomains/tests/views.py
subdomains/tests/urls/__init__.py
subdomains/tests/urls/api.py
subdomains/tests/urls/application.py
subdomains/tests/urls/default.py
subdomains/tests/urls/marketing.py